README.md
setup.cfg
setup.py
BrightnessBooster/__init__.py
BrightnessBooster/brightnessbooster.py
BrightnessBooster.egg-info/PKG-INFO
BrightnessBooster.egg-info/SOURCES.txt
BrightnessBooster.egg-info/dependency_links.txt
BrightnessBooster.egg-info/requires.txt
BrightnessBooster.egg-info/top_level.txt