Metadata-Version: 2.1
Name: BrightnessBooster
Version: 1.0.8
Summary: The code enhances an image's brightness and contrast
Home-page: UNKNOWN
Author: necros2604
Author-email: bair1hasykov@gmail.com
License: UNKNOWN
Platform: UNKNOWN
